valer.core.spotlight-1.0.3rc11-nspkg.pth
senaite/core/spotlight/__init__.py
senaite/core/spotlight/adapters.py
senaite/core/spotlight/configure.zcml
senaite/core/spotlight/interfaces.py
senaite/core/spotlight/setuphandlers.py
senaite/core/spotlight/viewlets.py
senaite/core/spotlight/views.py
senaite/core/spotlight/profiles/default/cssregistry.xml
senaite/core/spotlight/profiles/default/jsregistry.xml
senaite/core/spotlight/profiles/default/metadata.xml
senaite/core/spotlight/profiles/default/senaite.core.spotlight.txt
senaite/core/spotlight/profiles/uninstall/cssregistry.xml
senaite/core/spotlight/profiles/uninstall/jsregistry.xml
senaite/core/spotlight/profiles/uninstall/metadata.xml
senaite/core/spotlight/profiles/uninstall/senaite.core.spotlight.uninstall.txt
senaite/core/spotlight/static/js/senaite.core.spotlight.js
senaite/core/spotlight/templates/spotlight.pt
senaite/core/spotlight/templates/spotlight_trigger_viewlet.pt
senaite/core/spotlight/templates/spotlight_viewlet.pt
valer.core.spotlight-1.0.3rc11.dist-info/DESCRIPTION.rst
valer.core.spotlight-1.0.3rc11.dist-info/METADATA
valer.core.spotlight-1.0.3rc11.dist-info/RECORD
valer.core.spotlight-1.0.3rc11.dist-info/WHEEL
valer.core.spotlight-1.0.3rc11.dist-info/entry_points.txt
valer.core.spotlight-1.0.3rc11.dist-info/metadata.json
valer.core.spotlight-1.0.3rc11.dist-info/namespace_packages.txt
valer.core.spotlight-1.0.3rc11.dist-info/top_level.txt
