Metadata-Version: 2.0
Name: valer.core.spotlight
Version: 1.0.3rc11
Summary: MacOS like Spotlight search
Home-page: https://github.com/valeriozhang/senaite.core.spotlight
Author: Valer Group LLC
Author-email: valerio.zhang@valer.us
License: GPLv2
Platform: UNKNOWN
Classifier: Framework :: Plone
Classifier: Framework :: Zope2
Classifier: Programming Language :: Python
Classifier: Development Status :: 5 - Production/Stable
Classifier: License :: OSI Approved :: GNU General Public License v2 (GPLv2)
Provides-Extra: test
Requires-Dist: setuptools
Requires-Dist: valer.core (>=1.3.5rc11)
Requires-Dist: valer.jsonapi (>=1.2.3rc11)
Provides-Extra: test
Requires-Dist: plone.app.testing; extra == 'test'
Requires-Dist: unittest2; extra == 'test'
